quantkits/__init__.py
quantkits/api/__init__.py
quantkits/api/quantapi.py
quantkits/common/__init__.py
quantkits/common/decorators.py
quantkits/common/util.py
quantkits/db/__init__.py
quantkits/db/mysql.py
quantkits/logger/__init__.py
quantkits/message/__init__.py
quantkits/message/rabbitmq_client.py
quantkits/security/__init__.py
quantkits/security/bond/__init__.py
quantkits/security/equity/__init__.py
quantkits/security/repo/__init__.py
quantkits/statistics/__init__.py
quantkits/time/__init__.py
quantkits/time/conversion.py
quantkits/web/__init__.py
quantkits/web/driver.py
quantkits/web/proxy.py
scripts/__init__.py
scripts/parse_log.py
quantkits-0.0.6.dist-info/METADATA
quantkits-0.0.6.dist-info/WHEEL
quantkits-0.0.6.dist-info/entry_points.txt
quantkits-0.0.6.dist-info/top_level.txt
quantkits-0.0.6.dist-info/RECORD
